a3json_struct/__init__.py
a3json_struct/errors.py
a3json_struct/json_struct.py
a3json_struct/struct.py
a3json_struct/fields/__init__.py
a3json_struct/fields/abstract_field.py
a3json_struct/fields/boolean_field.py
a3json_struct/fields/char_field.py
a3json_struct/fields/date_field.py
a3json_struct/fields/datetime_field.py
a3json_struct/fields/decimal_field.py
a3json_struct/fields/dict_field.py
a3json_struct/fields/float_field.py
a3json_struct/fields/int_date_field.py
a3json_struct/fields/integer_field.py
a3json_struct/fields/list_field.py
a3json_struct/fields/object_field.py
a3json_struct/fields/utils.py
a3json_struct/validators/__init__.py
a3json_struct/validators/abstract_limit_validator.py
a3json_struct/validators/max_length_validator.py
a3json_struct/validators/max_value_validator.py
a3json_struct/validators/min_length_validator.py
a3json_struct/validators/min_value_validator.py
a3json_struct/validators/regex_validator.py
a3json_struct-0.3.0.dist-info/LICENSE
a3json_struct-0.3.0.dist-info/METADATA
a3json_struct-0.3.0.dist-info/WHEEL
a3json_struct-0.3.0.dist-info/top_level.txt
a3json_struct-0.3.0.dist-info/RECORD
